comparxiv/__init__.py
comparxiv/command_line.py
comparxiv/comparxiv.py
comparxiv-0.1.9.dist-info/LICENSE
comparxiv-0.1.9.dist-info/METADATA
comparxiv-0.1.9.dist-info/WHEEL
comparxiv-0.1.9.dist-info/entry_points.txt
comparxiv-0.1.9.dist-info/top_level.txt
comparxiv-0.1.9.dist-info/RECORD
