Metadata-Version: 2.1
Name: comparxiv
Version: 0.1.9
Summary: Compare two versions of an arXiv preprint with latexdiff.
Home-page: http://github.com/temken/comparxiv
Author: Timon Emken
Author-email: emken@chalmers.se
License: MIT
Keywords: arxiv preprint comparison latexdiff latex
Platform: UNKNOWN
Requires-Dist: tqdm
Requires-Dist: argparse
Requires-Dist: requests
Requires-Dist: arxiv (==1.4.2)
